odoo/addons/product_abc_classification_sale/README.rst
odoo/addons/product_abc_classification_sale/__init__.py
odoo/addons/product_abc_classification_sale/__manifest__.py
odoo/addons/product_abc_classification_sale/i18n/product_abc_classification_sale.pot
odoo/addons/product_abc_classification_sale/migrations/13.0.1.0.0/post-migration.py
odoo/addons/product_abc_classification_sale/migrations/13.0.1.0.0/pre-migration.py
odoo/addons/product_abc_classification_sale/models/__init__.py
odoo/addons/product_abc_classification_sale/models/abc_classification_profile.py
odoo/addons/product_abc_classification_sale/models/product_product.py
odoo/addons/product_abc_classification_sale/models/product_template.py
odoo/addons/product_abc_classification_sale/readme/CONTRIBUTORS.rst
odoo/addons/product_abc_classification_sale/readme/DESCRIPTION.rst
odoo/addons/product_abc_classification_sale/readme/ROADMAP.rst
odoo/addons/product_abc_classification_sale/readme/USAGE.rst
odoo/addons/product_abc_classification_sale/static/description/icon.png
odoo/addons/product_abc_classification_sale/static/description/index.html
odoo/addons/product_abc_classification_sale/tests/__init__.py
odoo/addons/product_abc_classification_sale/tests/test_sale_product_classification.py
odoo/addons/product_abc_classification_sale/tests/test_sale_product_classification_common.py
odoo/addons/product_abc_classification_sale/views/product_views.xml
odoo13_addon_product_abc_classification_sale-13.0.1.0.1.dist-info/METADATA
odoo13_addon_product_abc_classification_sale-13.0.1.0.1.dist-info/WHEEL
odoo13_addon_product_abc_classification_sale-13.0.1.0.1.dist-info/top_level.txt
odoo13_addon_product_abc_classification_sale-13.0.1.0.1.dist-info/RECORD
